compositeai/.DS_Store
compositeai/__init__.py
compositeai/agents/__init__.py
compositeai/agents/base_agent.py
compositeai/agents/plan_agent.py
compositeai/drivers/__init__.py
compositeai/drivers/base_driver.py
compositeai/drivers/openai_driver.py
compositeai/tools/__init__.py
compositeai/tools/base_tool.py
compositeai/tools/google_tool.py
compositeai/tools/test_tool.py
compositeai/tools/web_scraper_tool.py
compositeai-0.1.9.dist-info/METADATA
compositeai-0.1.9.dist-info/WHEEL
compositeai-0.1.9.dist-info/RECORD
