Metadata-Version: 2.1
Name: compositeai
Version: 0.1.9
Summary: Composite.ai was developed to make it as easy as possible for developers to build advanced AI agent systems while sacrificing as little customizability and versatility as possible. Using our framework, you should be able to construct AI agent teams that can complete complicated tasks and define rules for their interactions in just a few lines of code.
Author: Leon Chen
Author-email: lrchen01@gmail.com
Requires-Python: >=3.11,<4.0
Classifier: Programming Language :: Python :: 3
Classifier: Programming Language :: Python :: 3.11
Classifier: Programming Language :: Python :: 3.12
Requires-Dist: beautifulsoup4 (>=4.12.3,<5.0.0)
Requires-Dist: openai (>=1.25.1,<2.0.0)
Requires-Dist: pydantic (>=2.7.1,<3.0.0)
Requires-Dist: python-dotenv (>=1.0.1,<2.0.0)
Requires-Dist: requests (>=2.31.0,<3.0.0)
